Tashaphyne-0.3.4.1.dist-info/DESCRIPTION.rst
Tashaphyne-0.3.4.1.dist-info/METADATA
Tashaphyne-0.3.4.1.dist-info/RECORD
Tashaphyne-0.3.4.1.dist-info/WHEEL
Tashaphyne-0.3.4.1.dist-info/metadata.json
Tashaphyne-0.3.4.1.dist-info/top_level.txt
tashaphyne/__init__.py
tashaphyne/affix_const.py
tashaphyne/arabic_const.py
tashaphyne/arabicstopwords.py
tashaphyne/normalize.py
tashaphyne/roots_const.py
tashaphyne/rootsdict.py
tashaphyne/stem_const.py
tashaphyne/stemming.py
tashaphyne/stopwords.py
tashaphyne/verb_stamp_const.py
