Metadata-Version: 1.1
Name: Tashaphyne
Version: 0.3.4.1
Summary: Tashaphyne Arabic Light Stemmer
Home-page: http://github.com/linuxscout/tashaphyne/
Author: Taha Zerrouki
Author-email: taha.zerrouki@gmail.com
License: GPL
Platform: UNKNOWN
Classifier: Development Status :: 5 - Production/Stable
Classifier: Natural Language :: Arabic
Classifier: Intended Audience :: Developers
Classifier: Operating System :: OS Independent
Classifier: Programming Language :: Python
Classifier: Topic :: Text Processing :: Linguistic
